bldrx/__init__.py
bldrx/cli.py
bldrx/engine.py
bldrx/plugins.py
bldrx/registry.py
bldrx/renderer.py
bldrx/telemetry.py
bldrx/templates/ci/ci.yml.j2
bldrx/templates/ci/ci_metadata.json
bldrx/templates/ci/deploy.yml.j2
bldrx/templates/docker/.dockerignore.j2
bldrx/templates/docker/Dockerfile.j2
bldrx/templates/docker/ci_metadata.json
bldrx/templates/example-template/README.md.j2
bldrx/templates/example-template/ci_metadata.json
bldrx/templates/github/CODEOWNERS.j2
bldrx/templates/github/CODE_OF_CONDUCT.md.j2
bldrx/templates/github/CONTRIBUTING.md.j2
bldrx/templates/github/SECURITY.md.j2
bldrx/templates/github/SUPPORT.md.j2
bldrx/templates/github/ci_metadata.json
bldrx/templates/github/.github/funding.yml.j2
bldrx/templates/github/.github/ISSUE_TEMPLATE/bug_report.md.j2
bldrx/templates/github/.github/ISSUE_TEMPLATE/feature_request.md.j2
bldrx/templates/licenses/README.md.j2
bldrx/templates/licenses/ci_metadata.json
bldrx/templates/licenses/AGPL-3.0/LICENSE.j2
bldrx/templates/licenses/AGPL-3.0/README.md.j2
bldrx/templates/licenses/Apache-2.0/LICENSE.j2
bldrx/templates/licenses/Artistic-2.0/LICENSE.j2
bldrx/templates/licenses/BSD-2-Clause/LICENSE.j2
bldrx/templates/licenses/BSD-2-Clause/README.md.j2
bldrx/templates/licenses/BSD-3-Clause/LICENSE.j2
bldrx/templates/licenses/Boost-1.0/LICENSE.j2
bldrx/templates/licenses/CC0-1.0/LICENSE.j2
bldrx/templates/licenses/EPL-2.0/LICENSE.j2
bldrx/templates/licenses/GPL-2.0/LICENSE.j2
bldrx/templates/licenses/GPL-3.0/LICENSE.j2
bldrx/templates/licenses/ISC/LICENSE.j2
bldrx/templates/licenses/ISC/README.md.j2
bldrx/templates/licenses/LGPL-3.0/LICENSE.j2
bldrx/templates/licenses/MIT/LICENSE.j2
bldrx/templates/licenses/MIT/README.md.j2
bldrx/templates/licenses/MPL-2.0/LICENSE.j2
bldrx/templates/licenses/UNLICENSE/LICENSE.j2
bldrx/templates/lint/.eslintrc.js.j2
bldrx/templates/lint/.prettierrc.j2
bldrx/templates/lint/ci_metadata.json
bldrx/templates/lint/pyproject.toml.j2
bldrx/templates/node-api/README.md.j2
bldrx-0.1.6.dist-info/licenses/LICENSE
bldrx-0.1.6.dist-info/METADATA
bldrx-0.1.6.dist-info/WHEEL
bldrx-0.1.6.dist-info/entry_points.txt
bldrx-0.1.6.dist-info/top_level.txt
bldrx-0.1.6.dist-info/RECORD
