Metadata-Version: 2.4
Name: bldrx
Version: 0.1.6
Summary: CLI-first scaffold & template injector
Author-email: VoxDroid <izeno.contact@gmail.com>
License-Expression: MIT
Project-URL: Repository, https://github.com/VoxDroid/bldrx
Project-URL: Homepage, https://github.com/VoxDroid/bldrx
Keywords: scaffold,template,cli,boilerplate,project
Classifier: Programming Language :: Python :: 3
Classifier: Programming Language :: Python :: 3 :: Only
Classifier: Programming Language :: Python :: 3.9
Classifier: Programming Language :: Python :: 3.10
Classifier: Programming Language :: Python :: 3.11
Classifier: Intended Audience :: Developers
Classifier: Topic :: Software Development :: Build Tools
Requires-Python: >=3.9
License-File: LICENSE
Dynamic: license-file
